bin/__init__.py
bin/association_cli.py
bin/fink_fat_cli.py
bin/offline_cli.py
bin/orbit_cli.py
bin/stat_cli.py
bin/utils_cli.py
fink_fat/__init__.py
fink_fat/associations/__init__.py
fink_fat/associations/associations.py
fink_fat/associations/inter_night_associations.py
fink_fat/associations/intra_night_association.py
fink_fat/data/fink_fat.conf
fink_fat/data/month=03
fink_fat/data/month=04
fink_fat/data/month=05
fink_fat/data/month=06
fink_fat/data/month=07
fink_fat/orbit_fitting/AST17.bai_431_fcct
fink_fat/orbit_fitting/AST17.bep_431_fcct
fink_fat/orbit_fitting/__init__.py
fink_fat/orbit_fitting/ephem.py
fink_fat/orbit_fitting/orbfit_cluster.py
fink_fat/orbit_fitting/orbfit_local.py
fink_fat/orbit_fitting/orbfit_merger.py
fink_fat/orbit_fitting/template.oop
fink_fat/others/__init__.py
fink_fat/others/night_report.py
fink_fat/others/performance_test.py
fink_fat/others/plot_perf_test.py
fink_fat/others/utils.py
fink_fat/test/__init__.py
fink_fat/test/continuous_integration.py
fink_fat/test/test_sample.py
fink_fat-0.6.3.dist-info/LICENSE
fink_fat-0.6.3.dist-info/METADATA
fink_fat-0.6.3.dist-info/WHEEL
fink_fat-0.6.3.dist-info/entry_points.txt
fink_fat-0.6.3.dist-info/top_level.txt
fink_fat-0.6.3.dist-info/RECORD
