Metadata-Version: 2.1
Name: fink-fat
Version: 0.6.3
Summary: Associations of astronomical alerts to detect moving objects
Home-page: https://github.com/FusRoman/fink-fat
Author: Roman Le Montagner
Author-email: roman.le-montagner@ijclab.in2p3.fr
License: Apache-2.0 License
Project-URL: Documentation, https://github.com/FusRoman/fink-fat/wiki
Project-URL: Source, https://github.com/FusRoman/fink-fat
Platform: Linux Debian distribution
Requires-Python: >=3.7
License-File: LICENSE
Requires-Dist: docopt (>=0.6.2)
Requires-Dist: terminaltables (>=3.1.10)
Requires-Dist: fink-science (>=0.5.1)
Requires-Dist: fink-utils (>=0.3.0)
Requires-Dist: numpy (>=1.17)
Requires-Dist: pandas (>=1.3.5)
Requires-Dist: scikit-learn (>=1.0.2)
Requires-Dist: astropy (>=4.2.1)
